{
  "Routes": [

    // ================= Authentication =================
    {
      "DownstreamPathTemplate": "/api/Authentication/{everything}",
      "DownstreamScheme": "http",
      "DownstreamHostAndPorts": [
        {
          "Host": "localhost",
          "Port": 7001
        }
      ],
      "UpstreamPathTemplate": "/api/Authentication/{everything}",
      "UpstreamHttpMethod": [ "GET", "POST", "PUT", "DELETE" ]
    },

    // ================= CivicHub Admin =================
    {
      "DownstreamPathTemplate": "/api/Dashboard/{everything}",
      "DownstreamScheme": "http",
      "DownstreamHostAndPorts": [
        {
          "Host": "localhost",
          "Port": 7002
        }
      ],
      "UpstreamPathTemplate": "/api/Dashboard/{everything}",
      "UpstreamHttpMethod": [ "GET", "POST", "PUT", "DELETE" ]
    },

    // ================= KIOSK SERVICE =================
    {
      "DownstreamPathTemplate": "/api/kiosk/{everything}",
      "DownstreamScheme": "http",
      "DownstreamHostAndPorts": [
        {
          "Host": "localhost",
          "Port": 7003
        }
      ],
      "UpstreamPathTemplate": "/api/kiosk/{everything}",
      "UpstreamHttpMethod": [ "GET", "POST", "PUT", "DELETE" ]
    },

    // ================= REPORT SERVICE =================
    {
      "DownstreamPathTemplate": "/api/Report/{everything}",
      "DownstreamScheme": "http",
      "DownstreamHostAndPorts": [
        {
          "Host": "localhost",
          "Port": 7004
        }
      ],
      "UpstreamPathTemplate": "/api/Report/{everything}",
      "UpstreamHttpMethod": [ "GET", "POST", "PUT", "DELETE" ]
    }
  ],

  "GlobalConfiguration": {
    "BaseUrl": "https://localhost:7000"
  }
}
